flask_alipay/__init__.py
Flask_ALIPAY-0.1.2.dist-info/METADATA
Flask_ALIPAY-0.1.2.dist-info/WHEEL
Flask_ALIPAY-0.1.2.dist-info/top_level.txt
Flask_ALIPAY-0.1.2.dist-info/RECORD
